[
 {
  "RuleID": "generic-api-key",
  "Description": "Detected a Generic API Key, potentially exposing access to various services and sensitive operations.",
  "StartLine": 88,
  "EndLine": 88,
  "StartColumn": 4,
  "EndColumn": 51,
  "Match": "password: 'REDACTED'",
  "Secret": "REDACTED",
  "File": "data/static/users.yml",
  "SymlinkFile": "",
  "Commit": "",
  "Entropy": 4.32924,
  "Author": "",
  "Email": "",
  "Date": "",
  "Message": "",
  "Tags": [],
  "Fingerprint": "data/static/users.yml:generic-api-key:88"
 },
 {
  "RuleID": "generic-api-key",
  "Description": "Detected a Generic API Key, potentially exposing access to various services and sensitive operations.",
  "StartLine": 150,
  "EndLine": 150,
  "StartColumn": 4,
  "EndColumn": 48,
  "Match": "totpSecret: REDACTED\r",
  "Secret": "REDACTED",
  "File": "data/static/users.yml",
  "SymlinkFile": "",
  "Commit": "",
  "Entropy": 4.35141,
  "Author": "",
  "Email": "",
  "Date": "",
  "Message": "",
  "Tags": [],
  "Fingerprint": "data/static/users.yml:generic-api-key:150"
 },
 {
  "RuleID": "jwt",
  "Description": "Uncovered a JSON Web Token, which may lead to unauthorized access to web applications and sensitive user data.",
  "StartLine": 61,
  "EndLine": 61,
  "StartColumn": 37,
  "EndColumn": 164,
  "Match": "REDACTED'",
  "Secret": "REDACTED",
  "File": "frontend/src/app/last-login-ip/last-login-ip.component.spec.ts",
  "SymlinkFile": "",
  "Commit": "",
  "Entropy": 5.494293,
  "Author": "",
  "Email": "",
  "Date": "",
  "Message": "",
  "Tags": [],
  "Fingerprint": "frontend/src/app/last-login-ip/last-login-ip.component.spec.ts:jwt:61"
 },
 {
  "RuleID": "generic-api-key",
  "Description": "Detected a Generic API Key, potentially exposing access to various services and sensitive operations.",
  "StartLine": 67,
  "EndLine": 67,
  "StartColumn": 28,
  "EndColumn": 133,
  "Match": "token', 'REDACTED'",
  "Secret": "REDACTED",
  "File": "frontend/src/app/last-login-ip/last-login-ip.component.spec.ts",
  "SymlinkFile": "",
  "Commit": "",
  "Entropy": 5.321585,
  "Author": "",
  "Email": "",
  "Date": "",
  "Message": "",
  "Tags": [],
  "Fingerprint": "frontend/src/app/last-login-ip/last-login-ip.component.spec.ts:generic-api-key:67"
 },
 {
  "RuleID": "jwt",
  "Description": "Uncovered a JSON Web Token, which may lead to unauthorized access to web applications and sensitive user data.",
  "StartLine": 38,
  "EndLine": 38,
  "StartColumn": 37,
  "EndColumn": 192,
  "Match": "REDACTED'",
  "Secret": "REDACTED",
  "File": "frontend/src/app/app.guard.spec.ts",
  "SymlinkFile": "",
  "Commit": "",
  "Entropy": 5.4440703,
  "Author": "",
  "Email": "",
  "Date": "",
  "Message": "",
  "Tags": [],
  "Fingerprint": "frontend/src/app/app.guard.spec.ts:jwt:38"
 },
 {
  "RuleID": "generic-api-key",
  "Description": "Detected a Generic API Key, potentially exposing access to various services and sensitive operations.",
  "StartLine": 84,
  "EndLine": 84,
  "StartColumn": 78,
  "EndColumn": 109,
  "Match": "password: 'REDACTED'",
  "Secret": "REDACTED",
  "File": "frontend/src/app/oauth/oauth.component.spec.ts",
  "SymlinkFile": "",
  "Commit": "",
  "Entropy": 3.9219282,
  "Author": "",
  "Email": "",
  "Date": "",
  "Message": "",
  "Tags": [],
  "Fingerprint": "frontend/src/app/oauth/oauth.component.spec.ts:generic-api-key:84"
 },
 {
  "RuleID": "generic-api-key",
  "Description": "Detected a Generic API Key, potentially exposing access to various services and sensitive operations.",
  "StartLine": 84,
  "EndLine": 84,
  "StartColumn": 112,
  "EndColumn": 149,
  "Match": "passwordRepeat: 'REDACTED'",
  "Secret": "REDACTED",
  "File": "frontend/src/app/oauth/oauth.component.spec.ts",
  "SymlinkFile": "",
  "Commit": "",
  "Entropy": 3.9219282,
  "Author": "",
  "Email": "",
  "Date": "",
  "Message": "",
  "Tags": [],
  "Fingerprint": "frontend/src/app/oauth/oauth.component.spec.ts:generic-api-key:84"
 },
 {
  "RuleID": "generic-api-key",
  "Description": "Detected a Generic API Key, potentially exposing access to various services and sensitive operations.",
  "StartLine": 91,
  "EndLine": 91,
  "StartColumn": 79,
  "EndColumn": 110,
  "Match": "password: 'REDACTED'",
  "Secret": "REDACTED",
  "File": "frontend/src/app/oauth/oauth.component.spec.ts",
  "SymlinkFile": "",
  "Commit": "",
  "Entropy": 3.9219282,
  "Author": "",
  "Email": "",
  "Date": "",
  "Message": "",
  "Tags": [],
  "Fingerprint": "frontend/src/app/oauth/oauth.component.spec.ts:generic-api-key:91"
 },
 {
  "RuleID": "generic-api-key",
  "Description": "Detected a Generic API Key, potentially exposing access to various services and sensitive operations.",
  "StartLine": 34,
  "EndLine": 34,
  "StartColumn": 8,
  "EndColumn": 69,
  "Match": "BeeTokenAddress = 'REDACTED'",
  "Secret": "REDACTED",
  "File": "frontend/src/app/faucet/faucet.component.ts",
  "SymlinkFile": "",
  "Commit": "",
  "Entropy": 4.2368574,
  "Author": "",
  "Email": "",
  "Date": "",
  "Message": "",
  "Tags": [],
  "Fingerprint": "frontend/src/app/faucet/faucet.component.ts:generic-api-key:34"
 },
 {
  "RuleID": "generic-api-key",
  "Description": "Detected a Generic API Key, potentially exposing access to various services and sensitive operations.",
  "StartLine": 65,
  "EndLine": 65,
  "StartColumn": 134,
  "EndColumn": 193,
  "Match": "req.body.password === 'REDACTED'",
  "Secret": "REDACTED",
  "File": "routes/login.ts",
  "SymlinkFile": "",
  "Commit": "",
  "Entropy": 4.32924,
  "Author": "",
  "Email": "",
  "Date": "",
  "Message": "",
  "Tags": [],
  "Fingerprint": "routes/login.ts:generic-api-key:65"
 },
 {
  "RuleID": "generic-api-key",
  "Description": "Detected a Generic API Key, potentially exposing access to various services and sensitive operations.",
  "StartLine": 101,
  "EndLine": 101,
  "StartColumn": 10,
  "EndColumn": 57,
  "Match": "password: 'REDACTED'",
  "Secret": "REDACTED",
  "File": "test/api/basketApiSpec.ts",
  "SymlinkFile": "",
  "Commit": "",
  "Entropy": 4.32924,
  "Author": "",
  "Email": "",
  "Date": "",
  "Message": "",
  "Tags": [],
  "Fingerprint": "test/api/basketApiSpec.ts:generic-api-key:101"
 },
 {
  "RuleID": "generic-api-key",
  "Description": "Detected a Generic API Key, potentially exposing access to various services and sensitive operations.",
  "StartLine": 108,
  "EndLine": 108,
  "StartColumn": 10,
  "EndColumn": 57,
  "Match": "password: 'REDACTED'",
  "Secret": "REDACTED",
  "File": "test/api/chatBotSpec.ts",
  "SymlinkFile": "",
  "Commit": "",
  "Entropy": 4.32924,
  "Author": "",
  "Email": "",
  "Date": "",
  "Message": "",
  "Tags": [],
  "Fingerprint": "test/api/chatBotSpec.ts:generic-api-key:108"
 },
 {
  "RuleID": "generic-api-key",
  "Description": "Detected a Generic API Key, potentially exposing access to various services and sensitive operations.",
  "StartLine": 140,
  "EndLine": 140,
  "StartColumn": 10,
  "EndColumn": 57,
  "Match": "password: 'REDACTED'",
  "Secret": "REDACTED",
  "File": "test/api/chatBotSpec.ts",
  "SymlinkFile": "",
  "Commit": "",
  "Entropy": 4.32924,
  "Author": "",
  "Email": "",
  "Date": "",
  "Message": "",
  "Tags": [],
  "Fingerprint": "test/api/chatBotSpec.ts:generic-api-key:140"
 },
 {
  "RuleID": "generic-api-key",
  "Description": "Detected a Generic API Key, potentially exposing access to various services and sensitive operations.",
  "StartLine": 174,
  "EndLine": 174,
  "StartColumn": 10,
  "EndColumn": 57,
  "Match": "password: 'REDACTED'",
  "Secret": "REDACTED",
  "File": "test/api/chatBotSpec.ts",
  "SymlinkFile": "",
  "Commit": "",
  "Entropy": 4.32924,
  "Author": "",
  "Email": "",
  "Date": "",
  "Message": "",
  "Tags": [],
  "Fingerprint": "test/api/chatBotSpec.ts:generic-api-key:174"
 },
 {
  "RuleID": "generic-api-key",
  "Description": "Detected a Generic API Key, potentially exposing access to various services and sensitive operations.",
  "StartLine": 250,
  "EndLine": 250,
  "StartColumn": 10,
  "EndColumn": 57,
  "Match": "password: 'REDACTED'",
  "Secret": "REDACTED",
  "File": "test/api/chatBotSpec.ts",
  "SymlinkFile": "",
  "Commit": "",
  "Entropy": 4.32924,
  "Author": "",
  "Email": "",
  "Date": "",
  "Message": "",
  "Tags": [],
  "Fingerprint": "test/api/chatBotSpec.ts:generic-api-key:250"
 },
 {
  "RuleID": "generic-api-key",
  "Description": "Detected a Generic API Key, potentially exposing access to various services and sensitive operations.",
  "StartLine": 37,
  "EndLine": 37,
  "StartColumn": 10,
  "EndColumn": 57,
  "Match": "password: 'REDACTED'",
  "Secret": "REDACTED",
  "File": "test/api/erasureRequestApiSpec.ts",
  "SymlinkFile": "",
  "Commit": "",
  "Entropy": 4.32924,
  "Author": "",
  "Email": "",
  "Date": "",
  "Message": "",
  "Tags": [],
  "Fingerprint": "test/api/erasureRequestApiSpec.ts:generic-api-key:37"
 },
 {
  "RuleID": "generic-api-key",
  "Description": "Detected a Generic API Key, potentially exposing access to various services and sensitive operations.",
  "StartLine": 64,
  "EndLine": 64,
  "StartColumn": 10,
  "EndColumn": 57,
  "Match": "password: 'REDACTED'",
  "Secret": "REDACTED",
  "File": "test/api/erasureRequestApiSpec.ts",
  "SymlinkFile": "",
  "Commit": "",
  "Entropy": 4.32924,
  "Author": "",
  "Email": "",
  "Date": "",
  "Message": "",
  "Tags": [],
  "Fingerprint": "test/api/erasureRequestApiSpec.ts:generic-api-key:64"
 },
 {
  "RuleID": "generic-api-key",
  "Description": "Detected a Generic API Key, potentially exposing access to various services and sensitive operations.",
  "StartLine": 80,
  "EndLine": 80,
  "StartColumn": 18,
  "EndColumn": 65,
  "Match": "password: 'REDACTED'",
  "Secret": "REDACTED",
  "File": "test/api/erasureRequestApiSpec.ts",
  "SymlinkFile": "",
  "Commit": "",
  "Entropy": 4.32924,
  "Author": "",
  "Email": "",
  "Date": "",
  "Message": "",
  "Tags": [],
  "Fingerprint": "test/api/erasureRequestApiSpec.ts:generic-api-key:80"
 },
 {
  "RuleID": "generic-api-key",
  "Description": "Detected a Generic API Key, potentially exposing access to various services and sensitive operations.",
  "StartLine": 99,
  "EndLine": 99,
  "StartColumn": 10,
  "EndColumn": 57,
  "Match": "password: 'REDACTED'",
  "Secret": "REDACTED",
  "File": "test/api/erasureRequestApiSpec.ts",
  "SymlinkFile": "",
  "Commit": "",
  "Entropy": 4.32924,
  "Author": "",
  "Email": "",
  "Date": "",
  "Message": "",
  "Tags": [],
  "Fingerprint": "test/api/erasureRequestApiSpec.ts:generic-api-key:99"
 },
 {
  "RuleID": "generic-api-key",
  "Description": "Detected a Generic API Key, potentially exposing access to various services and sensitive operations.",
  "StartLine": 119,
  "EndLine": 119,
  "StartColumn": 10,
  "EndColumn": 57,
  "Match": "password: 'REDACTED'",
  "Secret": "REDACTED",
  "File": "test/api/erasureRequestApiSpec.ts",
  "SymlinkFile": "",
  "Commit": "",
  "Entropy": 4.32924,
  "Author": "",
  "Email": "",
  "Date": "",
  "Message": "",
  "Tags": [],
  "Fingerprint": "test/api/erasureRequestApiSpec.ts:generic-api-key:119"
 },
 {
  "RuleID": "generic-api-key",
  "Description": "Detected a Generic API Key, potentially exposing access to various services and sensitive operations.",
  "StartLine": 140,
  "EndLine": 140,
  "StartColumn": 10,
  "EndColumn": 57,
  "Match": "password: 'REDACTED'",
  "Secret": "REDACTED",
  "File": "test/api/erasureRequestApiSpec.ts",
  "SymlinkFile": "",
  "Commit": "",
  "Entropy": 4.32924,
  "Author": "",
  "Email": "",
  "Date": "",
  "Message": "",
  "Tags": [],
  "Fingerprint": "test/api/erasureRequestApiSpec.ts:generic-api-key:140"
 },
 {
  "RuleID": "generic-api-key",
  "Description": "Detected a Generic API Key, potentially exposing access to various services and sensitive operations.",
  "StartLine": 120,
  "EndLine": 120,
  "StartColumn": 10,
  "EndColumn": 57,
  "Match": "password: 'REDACTED'",
  "Secret": "REDACTED",
  "File": "test/api/feedbackApiSpec.ts",
  "SymlinkFile": "",
  "Commit": "",
  "Entropy": 4.32924,
  "Author": "",
  "Email": "",
  "Date": "",
  "Message": "",
  "Tags": [],
  "Fingerprint": "test/api/feedbackApiSpec.ts:generic-api-key:120"
 },
 {
  "RuleID": "generic-api-key",
  "Description": "Detected a Generic API Key, potentially exposing access to various services and sensitive operations.",
  "StartLine": 153,
  "EndLine": 153,
  "StartColumn": 10,
  "EndColumn": 57,
  "Match": "password: 'REDACTED'",
  "Secret": "REDACTED",
  "File": "test/api/feedbackApiSpec.ts",
  "SymlinkFile": "",
  "Commit": "",
  "Entropy": 4.32924,
  "Author": "",
  "Email": "",
  "Date": "",
  "Message": "",
  "Tags": [],
  "Fingerprint": "test/api/feedbackApiSpec.ts:generic-api-key:153"
 },
 {
  "RuleID": "generic-api-key",
  "Description": "Detected a Generic API Key, potentially exposing access to various services and sensitive operations.",
  "StartLine": 21,
  "EndLine": 21,
  "StartColumn": 10,
  "EndColumn": 57,
  "Match": "password: 'REDACTED'",
  "Secret": "REDACTED",
  "File": "test/api/dataExportApiSpec.ts",
  "SymlinkFile": "",
  "Commit": "",
  "Entropy": 4.32924,
  "Author": "",
  "Email": "",
  "Date": "",
  "Message": "",
  "Tags": [],
  "Fingerprint": "test/api/dataExportApiSpec.ts:generic-api-key:21"
 },
 {
  "RuleID": "generic-api-key",
  "Description": "Detected a Generic API Key, potentially exposing access to various services and sensitive operations.",
  "StartLine": 48,
  "EndLine": 48,
  "StartColumn": 10,
  "EndColumn": 57,
  "Match": "password: 'REDACTED'",
  "Secret": "REDACTED",
  "File": "test/api/dataExportApiSpec.ts",
  "SymlinkFile": "",
  "Commit": "",
  "Entropy": 4.32924,
  "Author": "",
  "Email": "",
  "Date": "",
  "Message": "",
  "Tags": [],
  "Fingerprint": "test/api/dataExportApiSpec.ts:generic-api-key:48"
 },
 {
  "RuleID": "generic-api-key",
  "Description": "Detected a Generic API Key, potentially exposing access to various services and sensitive operations.",
  "StartLine": 77,
  "EndLine": 77,
  "StartColumn": 10,
  "EndColumn": 57,
  "Match": "password: 'REDACTED'",
  "Secret": "REDACTED",
  "File": "test/api/dataExportApiSpec.ts",
  "SymlinkFile": "",
  "Commit": "",
  "Entropy": 4.32924,
  "Author": "",
  "Email": "",
  "Date": "",
  "Message": "",
  "Tags": [],
  "Fingerprint": "test/api/dataExportApiSpec.ts:generic-api-key:77"
 },
 {
  "RuleID": "generic-api-key",
  "Description": "Detected a Generic API Key, potentially exposing access to various services and sensitive operations.",
  "StartLine": 7,
  "EndLine": 7,
  "StartColumn": 10,
  "EndColumn": 55,
  "Match": "totpSecret: 'REDACTED'",
  "Secret": "REDACTED",
  "File": "test/cypress/e2e/totpSetup.spec.ts",
  "SymlinkFile": "",
  "Commit": "",
  "Entropy": 4.35141,
  "Author": "",
  "Email": "",
  "Date": "",
  "Message": "",
  "Tags": [],
  "Fingerprint": "test/cypress/e2e/totpSetup.spec.ts:generic-api-key:7"
 },
 {
  "RuleID": "generic-api-key",
  "Description": "Detected a Generic API Key, potentially exposing access to various services and sensitive operations.",
  "StartLine": 112,
  "EndLine": 112,
  "StartColumn": 10,
  "EndColumn": 57,
  "Match": "password: 'REDACTED'",
  "Secret": "REDACTED",
  "File": "test/api/productReviewApiSpec.ts",
  "SymlinkFile": "",
  "Commit": "",
  "Entropy": 4.32924,
  "Author": "",
  "Email": "",
  "Date": "",
  "Message": "",
  "Tags": [],
  "Fingerprint": "test/api/productReviewApiSpec.ts:generic-api-key:112"
 },
 {
  "RuleID": "generic-api-key",
  "Description": "Detected a Generic API Key, potentially exposing access to various services and sensitive operations.",
  "StartLine": 132,
  "EndLine": 132,
  "StartColumn": 10,
  "EndColumn": 57,
  "Match": "password: 'REDACTED'",
  "Secret": "REDACTED",
  "File": "test/api/productReviewApiSpec.ts",
  "SymlinkFile": "",
  "Commit": "",
  "Entropy": 4.32924,
  "Author": "",
  "Email": "",
  "Date": "",
  "Message": "",
  "Tags": [],
  "Fingerprint": "test/api/productReviewApiSpec.ts:generic-api-key:132"
 },
 {
  "RuleID": "generic-api-key",
  "Description": "Detected a Generic API Key, potentially exposing access to various services and sensitive operations.",
  "StartLine": 142,
  "EndLine": 142,
  "StartColumn": 10,
  "EndColumn": 57,
  "Match": "password: 'REDACTED'",
  "Secret": "REDACTED",
  "File": "test/api/loginApiSpec.ts",
  "SymlinkFile": "",
  "Commit": "",
  "Entropy": 4.32924,
  "Author": "",
  "Email": "",
  "Date": "",
  "Message": "",
  "Tags": [],
  "Fingerprint": "test/api/loginApiSpec.ts:generic-api-key:142"
 },
 {
  "RuleID": "generic-api-key",
  "Description": "Detected a Generic API Key, potentially exposing access to various services and sensitive operations.",
  "StartLine": 245,
  "EndLine": 245,
  "StartColumn": 10,
  "EndColumn": 57,
  "Match": "password: 'REDACTED'",
  "Secret": "REDACTED",
  "File": "test/api/loginApiSpec.ts",
  "SymlinkFile": "",
  "Commit": "",
  "Entropy": 4.32924,
  "Author": "",
  "Email": "",
  "Date": "",
  "Message": "",
  "Tags": [],
  "Fingerprint": "test/api/loginApiSpec.ts:generic-api-key:245"
 },
 {
  "RuleID": "generic-api-key",
  "Description": "Detected a Generic API Key, potentially exposing access to various services and sensitive operations.",
  "StartLine": 266,
  "EndLine": 266,
  "StartColumn": 10,
  "EndColumn": 57,
  "Match": "password: 'REDACTED'",
  "Secret": "REDACTED",
  "File": "test/api/loginApiSpec.ts",
  "SymlinkFile": "",
  "Commit": "",
  "Entropy": 4.32924,
  "Author": "",
  "Email": "",
  "Date": "",
  "Message": "",
  "Tags": [],
  "Fingerprint": "test/api/loginApiSpec.ts:generic-api-key:266"
 },
 {
  "RuleID": "private-key",
  "Description": "Identified a Private Key, which may compromise cryptographic security and sensitive data encryption.",
  "StartLine": 23,
  "EndLine": 23,
  "StartColumn": 22,
  "EndColumn": 901,
  "Match": "REDACTED",
  "Secret": "REDACTED",
  "File": "lib/insecurity.ts",
  "SymlinkFile": "",
  "Commit": "",
  "Entropy": 5.98135,
  "Author": "",
  "Email": "",
  "Date": "",
  "Message": "",
  "Tags": [],
  "Fingerprint": "lib/insecurity.ts:private-key:23"
 },
 {
  "RuleID": "generic-api-key",
  "Description": "Detected a Generic API Key, potentially exposing access to various services and sensitive operations.",
  "StartLine": 256,
  "EndLine": 256,
  "StartColumn": 10,
  "EndColumn": 57,
  "Match": "password: 'REDACTED'",
  "Secret": "REDACTED",
  "File": "test/api/userApiSpec.ts",
  "SymlinkFile": "",
  "Commit": "",
  "Entropy": 4.32924,
  "Author": "",
  "Email": "",
  "Date": "",
  "Message": "",
  "Tags": [],
  "Fingerprint": "test/api/userApiSpec.ts:generic-api-key:256"
 },
 {
  "RuleID": "jwt",
  "Description": "Uncovered a JSON Web Token, which may lead to unauthorized access to web applications and sensitive user data.",
  "StartLine": 302,
  "EndLine": 302,
  "StartColumn": 80,
  "EndColumn": 776,
  "Match": "REDACTED'",
  "Secret": "REDACTED",
  "File": "test/api/userApiSpec.ts",
  "SymlinkFile": "",
  "Commit": "",
  "Entropy": 5.7084465,
  "Author": "",
  "Email": "",
  "Date": "",
  "Message": "",
  "Tags": [],
  "Fingerprint": "test/api/userApiSpec.ts:jwt:302"
 },
 {
  "RuleID": "jwt",
  "Description": "Uncovered a JSON Web Token, which may lead to unauthorized access to web applications and sensitive user data.",
  "StartLine": 33,
  "EndLine": 33,
  "StartColumn": 27,
  "EndColumn": 390,
  "Match": "REDACTED'",
  "Secret": "REDACTED",
  "File": "test/server/currentUserSpec.ts",
  "SymlinkFile": "",
  "Commit": "",
  "Entropy": 5.8161607,
  "Author": "",
  "Email": "",
  "Date": "",
  "Message": "",
  "Tags": [],
  "Fingerprint": "test/server/currentUserSpec.ts:jwt:33"
 },
 {
  "RuleID": "jwt",
  "Description": "Uncovered a JSON Web Token, which may lead to unauthorized access to web applications and sensitive user data.",
  "StartLine": 36,
  "EndLine": 36,
  "StartColumn": 9,
  "EndColumn": 372,
  "Match": "REDACTED'",
  "Secret": "REDACTED",
  "File": "test/server/currentUserSpec.ts",
  "SymlinkFile": "",
  "Commit": "",
  "Entropy": 5.8161607,
  "Author": "",
  "Email": "",
  "Date": "",
  "Message": "",
  "Tags": [],
  "Fingerprint": "test/server/currentUserSpec.ts:jwt:36"
 },
 {
  "RuleID": "jwt",
  "Description": "Uncovered a JSON Web Token, which may lead to unauthorized access to web applications and sensitive user data.",
  "StartLine": 7,
  "EndLine": 7,
  "StartColumn": 13,
  "EndColumn": 148,
  "Match": "REDACTED'",
  "Secret": "REDACTED",
  "File": "test/cypress/e2e/forgedJwt.spec.ts",
  "SymlinkFile": "",
  "Commit": "",
  "Entropy": 5.3029537,
  "Author": "",
  "Email": "",
  "Date": "",
  "Message": "",
  "Tags": [],
  "Fingerprint": "test/cypress/e2e/forgedJwt.spec.ts:jwt:7"
 },
 {
  "RuleID": "jwt",
  "Description": "Uncovered a JSON Web Token, which may lead to unauthorized access to web applications and sensitive user data.",
  "StartLine": 22,
  "EndLine": 22,
  "StartColumn": 17,
  "EndColumn": 176,
  "Match": "REDACTED'",
  "Secret": "REDACTED",
  "File": "test/cypress/e2e/forgedJwt.spec.ts",
  "SymlinkFile": "",
  "Commit": "",
  "Entropy": 5.6491113,
  "Author": "",
  "Email": "",
  "Date": "",
  "Message": "",
  "Tags": [],
  "Fingerprint": "test/cypress/e2e/forgedJwt.spec.ts:jwt:22"
 },
 {
  "RuleID": "generic-api-key",
  "Description": "Detected a Generic API Key, potentially exposing access to various services and sensitive operations.",
  "StartLine": 36,
  "EndLine": 36,
  "StartColumn": 8,
  "EndColumn": 89,
  "Match": "privateKey: 'REDACTED'",
  "Secret": "REDACTED",
  "File": "test/api/web3Spec.ts",
  "SymlinkFile": "",
  "Commit": "",
  "Entropy": 3.7923596,
  "Author": "",
  "Email": "",
  "Date": "",
  "Message": "",
  "Tags": [],
  "Fingerprint": "test/api/web3Spec.ts:generic-api-key:36"
 },
 {
  "RuleID": "generic-api-key",
  "Description": "Detected a Generic API Key, potentially exposing access to various services and sensitive operations.",
  "StartLine": 48,
  "EndLine": 48,
  "StartColumn": 8,
  "EndColumn": 63,
  "Match": "privateKey: 'REDACTED'",
  "Secret": "REDACTED",
  "File": "test/api/web3Spec.ts",
  "SymlinkFile": "",
  "Commit": "",
  "Entropy": 3.8175802,
  "Author": "",
  "Email": "",
  "Date": "",
  "Message": "",
  "Tags": [],
  "Fingerprint": "test/api/web3Spec.ts:generic-api-key:48"
 },
 {
  "RuleID": "generic-api-key",
  "Description": "Detected a Generic API Key, potentially exposing access to various services and sensitive operations.",
  "StartLine": 60,
  "EndLine": 60,
  "StartColumn": 8,
  "EndColumn": 87,
  "Match": "privateKey: 'REDACTED'",
  "Secret": "REDACTED",
  "File": "test/api/web3Spec.ts",
  "SymlinkFile": "",
  "Commit": "",
  "Entropy": 3.8491814,
  "Author": "",
  "Email": "",
  "Date": "",
  "Message": "",
  "Tags": [],
  "Fingerprint": "test/api/web3Spec.ts:generic-api-key:60"
 },
 {
  "RuleID": "generic-api-key",
  "Description": "Detected a Generic API Key, potentially exposing access to various services and sensitive operations.",
  "StartLine": 126,
  "EndLine": 126,
  "StartColumn": 25,
  "EndColumn": 82,
  "Match": "GenerateAuthenticator', 'REDACTED'",
  "Secret": "REDACTED",
  "File": "test/cypress/e2e/login.spec.ts",
  "SymlinkFile": "",
  "Commit": "",
  "Entropy": 4.35141,
  "Author": "",
  "Email": "",
  "Date": "",
  "Message": "",
  "Tags": [],
  "Fingerprint": "test/cypress/e2e/login.spec.ts:generic-api-key:126"
 },
 {
  "RuleID": "generic-api-key",
  "Description": "Detected a Generic API Key, potentially exposing access to various services and sensitive operations.",
  "StartLine": 175,
  "EndLine": 175,
  "StartColumn": 8,
  "EndColumn": 53,
  "Match": "totpSecret: 'REDACTED'",
  "Secret": "REDACTED",
  "File": "test/api/2faSpec.ts",
  "SymlinkFile": "",
  "Commit": "",
  "Entropy": 4.35141,
  "Author": "",
  "Email": "",
  "Date": "",
  "Message": "",
  "Tags": [],
  "Fingerprint": "test/api/2faSpec.ts:generic-api-key:175"
 },
 {
  "RuleID": "generic-api-key",
  "Description": "Detected a Generic API Key, potentially exposing access to various services and sensitive operations.",
  "StartLine": 370,
  "EndLine": 370,
  "StartColumn": 12,
  "EndColumn": 58,
  "Match": "totpSecret = 'REDACTED'",
  "Secret": "REDACTED",
  "File": "test/api/2faSpec.ts",
  "SymlinkFile": "",
  "Commit": "",
  "Entropy": 4.35141,
  "Author": "",
  "Email": "",
  "Date": "",
  "Message": "",
  "Tags": [],
  "Fingerprint": "test/api/2faSpec.ts:generic-api-key:370"
 },
 {
  "RuleID": "jwt",
  "Description": "Uncovered a JSON Web Token, which may lead to unauthorized access to web applications and sensitive user data.",
  "StartLine": 263,
  "EndLine": 263,
  "StartColumn": 47,
  "EndColumn": 182,
  "Match": "REDACTED'",
  "Secret": "REDACTED",
  "File": "test/server/verifySpec.ts",
  "SymlinkFile": "",
  "Commit": "",
  "Entropy": 5.3029537,
  "Author": "",
  "Email": "",
  "Date": "",
  "Message": "",
  "Tags": [],
  "Fingerprint": "test/server/verifySpec.ts:jwt:263"
 },
 {
  "RuleID": "jwt",
  "Description": "Uncovered a JSON Web Token, which may lead to unauthorized access to web applications and sensitive user data.",
  "StartLine": 275,
  "EndLine": 275,
  "StartColumn": 47,
  "EndColumn": 167,
  "Match": "REDACTED'",
  "Secret": "REDACTED",
  "File": "test/server/verifySpec.ts",
  "SymlinkFile": "",
  "Commit": "",
  "Entropy": 5.3197346,
  "Author": "",
  "Email": "",
  "Date": "",
  "Message": "",
  "Tags": [],
  "Fingerprint": "test/server/verifySpec.ts:jwt:275"
 },
 {
  "RuleID": "jwt",
  "Description": "Uncovered a JSON Web Token, which may lead to unauthorized access to web applications and sensitive user data.",
  "StartLine": 297,
  "EndLine": 297,
  "StartColumn": 49,
  "EndColumn": 208,
  "Match": "REDACTED'",
  "Secret": "REDACTED",
  "File": "test/server/verifySpec.ts",
  "SymlinkFile": "",
  "Commit": "",
  "Entropy": 5.6027975,
  "Author": "",
  "Email": "",
  "Date": "",
  "Message": "",
  "Tags": [],
  "Fingerprint": "test/server/verifySpec.ts:jwt:297"
 },
 {
  "RuleID": "jwt",
  "Description": "Uncovered a JSON Web Token, which may lead to unauthorized access to web applications and sensitive user data.",
  "StartLine": 309,
  "EndLine": 309,
  "StartColumn": 49,
  "EndColumn": 193,
  "Match": "REDACTED'",
  "Secret": "REDACTED",
  "File": "test/server/verifySpec.ts",
  "SymlinkFile": "",
  "Commit": "",
  "Entropy": 5.5496736,
  "Author": "",
  "Email": "",
  "Date": "",
  "Message": "",
  "Tags": [],
  "Fingerprint": "test/server/verifySpec.ts:jwt:309"
 }
]
